flask_eureka/__init__.py
flask_eureka/ec2metadata.py
flask_eureka/eureka.py
flask_eureka/eurekaclient.py
flask_eureka/hostinfo.py
flask_eureka/httpclient.py
flask_eureka_client-1.0.2.dist-info/LICENSE
flask_eureka_client-1.0.2.dist-info/METADATA
flask_eureka_client-1.0.2.dist-info/WHEEL
flask_eureka_client-1.0.2.dist-info/top_level.txt
flask_eureka_client-1.0.2.dist-info/RECORD
