Metadata-Version: 2.1
Name: flask-eureka-client
Version: 1.0.2
Summary: Eureka client library for flask
Home-page: https://github.com/IndustryApps/flask-eureka
Author: IndustryApps
Author-email: libin-p@industryapps.net
License: MIT
Keywords: microservice,netflix,flask,eureka,industryapps
Platform: UNKNOWN
Classifier: Programming Language :: Python :: 3
Classifier: Programming Language :: Python :: 3.3
Classifier: Programming Language :: Python :: 3.4
Classifier: Programming Language :: Python :: 3.5
License-File: LICENSE
